{
    "configurations": [
        {
            "name": "Win32",
            "includePath": [
                "C:/Users/IBM_ADMIN/Documents/Arduino/libraries"
            ],
            "browse": {
                "limitSymbolsToIncludedHeaders": false,
                "path": [
                    "C:\\Users\\IBM_ADMIN\\AppData\\Local\\Arduino15\\packages\\arduino\\hardware\\samd\\1.6.15\\cores\\arduino",
                    "${workspaceRoot}"
                ]
            },
            "intelliSenseMode": "msvc-x64"
        }
    ],
    "version": 4
}